legends/__init__.py
legends/__main__.py
legends/consensus.py
legends/contracts.py
legends/engines.py
legends/pantheon.py
legends/scaffold.py
pantheon_legends-0.4.0.dist-info/licenses/LICENSE
pantheon_legends-0.4.0.dist-info/METADATA
pantheon_legends-0.4.0.dist-info/WHEEL
pantheon_legends-0.4.0.dist-info/top_level.txt
pantheon_legends-0.4.0.dist-info/RECORD
