Metadata-Version: 2.4
Name: pantheon-legends
Version: 0.4.0
Summary: Python framework for implementing financial market analysis legend engines with type-aware Traditional vs Scanner distinction
Author-email: SpartanDigital <spartandigital@icloud.com>
License-Expression: MIT
Project-URL: Homepage, https://github.com/SpartanDigitalDotNet/pantheon-legends
Project-URL: Repository, https://github.com/SpartanDigitalDotNet/pantheon-legends
Project-URL: Documentation, https://spartandigitaldotnet.github.io/pantheon-legends
Project-URL: Bug Tracker, https://github.com/SpartanDigitalDotNet/pantheon-legends/issues
Keywords: finance,trading,technical-analysis,market-analysis,legends
Classifier: Development Status :: 3 - Alpha
Classifier: Intended Audience :: Financial and Insurance Industry
Classifier: Intended Audience :: Developers
Classifier: Operating System :: OS Independent
Classifier: Programming Language :: Python :: 3
Classifier: Programming Language :: Python :: 3.8
Classifier: Programming Language :: Python :: 3.9
Classifier: Programming Language :: Python :: 3.10
Classifier: Programming Language :: Python :: 3.11
Classifier: Programming Language :: Python :: 3.12
Classifier: Topic :: Office/Business :: Financial
Classifier: Topic :: Scientific/Engineering :: Information Analysis
Requires-Python: >=3.8
License-File: LICENSE
Provides-Extra: dev
Requires-Dist: pytest>=7.0; extra == "dev"
Requires-Dist: pytest-asyncio>=0.21.0; extra == "dev"
Requires-Dist: black>=23.0; extra == "dev"
Requires-Dist: flake8>=6.0; extra == "dev"
Requires-Dist: mypy>=1.0; extra == "dev"
Requires-Dist: isort>=5.0; extra == "dev"
Dynamic: license-file
